pls2upl/__init__.py
pls2upl/cli.py
pls2upl/functions.py
pls2upl-0.0.5.dist-info/DESCRIPTION.rst
pls2upl-0.0.5.dist-info/METADATA
pls2upl-0.0.5.dist-info/RECORD
pls2upl-0.0.5.dist-info/WHEEL
pls2upl-0.0.5.dist-info/entry_points.txt
pls2upl-0.0.5.dist-info/metadata.json
pls2upl-0.0.5.dist-info/top_level.txt
