Metadata-Version: 2.0
Name: pls2upl
Version: 0.0.5
Summary: pls2upl is a command-line utility for converting PLS/M3U playlists to UPL
Home-page: https://gitlab.com/universal-playlist/pls2upl/
Author: Stavros Korokithakis
Author-email: hi@stavros.io
License: BSD
Keywords: music universal playlist pls m3u upl
Platform: UNKNOWN
Classifier: Development Status :: 2 - Pre-Alpha
Classifier: Intended Audience :: End Users/Desktop
Classifier: License :: OSI Approved :: BSD License
Classifier: Natural Language :: English
Classifier: Programming Language :: Python :: 3
Classifier: Programming Language :: Python :: 3.3
Classifier: Programming Language :: Python :: 3.4
Classifier: Programming Language :: Python :: 3.5
Requires-Dist: click (~=6.7)
Requires-Dist: mutagen (~=1.37)
